---
title: "Java Instrumentation API"
description: "Java Instrumentation API를 활용하여 코드 수정 없이 애플리케이션을 모니터링하고 분석하는 방법을 알아봅니다. Java 에이전트의 동작 원리, 바이트코드 조작 시점, 그리고 실제 활용 사례까지 Java의 강력한 계측 기능을 심층적으로 살펴봅니다."
tags: ["JAVA", "INSTRUMENTATION", "JVM", "BYTECODE", "AGENT", "BACKEND", "MONITORING", "APM"]
keywords: ["자바 인스트루멘테이션", "Java Instrumentation", "자바 에이전트", "Java Agent", "바이트코드 조작", "Bytecode Manipulation", "자바 모니터링", "코드 계측", "APM", "애플리케이션 성능 모니터링", "javaagent", "premain", "자바 프로파일링", "동적 계측", "ASM", "Javassist", "ByteBuddy"]
draft: false
hide_title: true
---

## 1. Java Instrumentation API 소개

- Java Instrumentation API는 JVM에서 실행 중인 Java 코드를 감시하고 조작할 수 있는 메커니즘을 제공합니다.
- JDK 1.5에서 처음 도입되었으며, 이후 버전에서 지속적으로 개선되었습니다.
- 이 API의 핵심 가치는 원본 소스 코드를 수정하지 않고도 프로그램의 동작을 관찰, 수정, 확장할 수 있다는 점입니다.
- 애플리케이션 성능 모니터링(APM), 프로파일링, 커버리지 분석, 보안 검사 등 다양한 툴이 이 API를 기반으로 구축됩니다.

### 1.1 Instrumentation의 원리

- Instrumentation은 바이트코드 수준에서 작동하며, 클래스가 로드될 때 또는 이미 로드된 클래스를 재정의하여 동작을 변경합니다.
- 일반적으로 특정 메서드의 시작과 끝에 추가 코드를 삽입하여 실행 시간, 메모리 사용량, 예외 발생 등을 측정합니다.
- 이 과정은 애플리케이션의 실행 코드 흐름에 영향을 주지만, 원본 소스 코드는 변경되지 않습니다.
- 런타임에 이루어지는 이러한 "코드 주입" 방식이 "코드 침투 없는 계측"을 가능하게 합니다.

## 2. Java Agent의 개념과 유형

- Java Agent는 Instrumentation API를 사용하여 클래스를 변환하는 특수한 Java 프로그램입니다.
- Java Agent는 애플리케이션의 메인 메서드가 실행되기 전(premain) 또는 실행 중(agentmain)에 로드될 수 있습니다.
- JAR 파일 형태로 패키징되며, 특수한 매니페스트 속성을 포함합니다.

### 2.1 정적 에이전트(Static Agent)

- JVM 시작 시 `-javaagent` 옵션을 통해 로드됩니다.
- `premain` 메서드를 구현해야 합니다.
- `premain` 메서드에서 ClassFileTransformer를 등록하여, 이후 각 클래스가 처음 로드될 때 바이트코드 변환이 이루어지도록 합니다.
- 애플리케이션 전체 생명주기에 걸쳐 모니터링하는 데 적합합니다.
- 예시: APM 툴(New Relic, AppDynamics), 코드 커버리지 도구(JaCoCo), 프로파일러(YourKit)

```java
public static void premain(String agentArgs, Instrumentation inst) {
    inst.addTransformer(new MyClassTransformer());
}
```

### 2.2 동적 에이전트(Dynamic Agent)

- 이미 실행 중인 JVM에 Attach API를 사용하여 동적으로 로드됩니다.
- `agentmain` 메서드를 구현해야 합니다.
  - 실행 중인 JVM에 연결하여 에이전트 JAR를 로드하면 agentmain 메서드가 호출됩니다.
- `agentmain` 메서드 안에서 이미 로드된 클래스의 재정의(retransformation)를 수행할 수 있습니다.
- 실행 중인 애플리케이션의 문제 진단이나 특정 조건에서만 모니터링이 필요한 경우 유용합니다.
- 예시: JVM 트러블슈팅 도구(Arthas, BTrace)

```java
public static void agentmain(String agentArgs, Instrumentation inst) {
    // ClassFileTransformer를 등록합니다. true 파라미터는 retransform 가능하게 설정
    inst.addTransformer(new MyClassTransformer(), true);
    
    // 이미 로드된 특정 클래스를 재변환합니다.
    // 이 시점에 등록된 transformer가 호출되어 실제 바이트코드 변환이 수행됩니다.
    inst.retransformClasses(TargetClass.class);
}
```

### 2.3 에이전트 JAR 매니페스트 설정

- Java Agent JAR 파일은 특수한 매니페스트 속성이 필요합니다.
- 정적 에이전트와 동적 에이전트의 매니페스트 설정이 다릅니다.

정적 에이전트 매니페스트(MANIFEST.MF) 예시:
```
Manifest-Version: 1.0
Premain-Class: com.example.MyJavaAgent
Can-Redefine-Classes: true
Can-Retransform-Classes: true
```

동적 에이전트 매니페스트(MANIFEST.MF) 예시:
```
Manifest-Version: 1.0
Agent-Class: com.example.MyJavaAgent
Can-Redefine-Classes: true
Can-Retransform-Classes: true
```

## 3. 바이트코드 변환 메커니즘

- Java 에이전트는 `ClassFileTransformer` 인터페이스를 구현하여 바이트코드를 변환합니다.
- 변환 과정에서 바이트코드 조작 라이브러리(ASM, Javassist, ByteBuddy 등)를 사용합니다.
- 이 프로세스는 원본 코드에는 영향을 주지 않으면서, 실행되는 코드를 변경합니다.

### 3.1 클래스 로드 및 변환 시점

- **클래스 로드 시점**: JVM이 클래스를 처음 로드할 때 발생합니다.
	- 클래스 로더가 클래스 파일을 찾고 바이트코드를 로드합니다.
	- 클래스가 로드되기 전에 등록된 `ClassFileTransformer`가 바이트코드를 변환합니다.
	- 변환된 바이트코드는 JVM의 클래스 정의에 사용됩니다.
- **클래스 재정의(Retransformation) 시점**: 이미 로드된 클래스의 바이트코드를 변경합니다.
	- `Instrumentation.retransformClasses()` 메서드를 통해 트리거됩니다.
	- 이미 생성된 객체의 동작도 변경할 수 있습니다.
	- 클래스 구조(필드 추가/삭제, 메서드 시그니처 변경 등)는 변경할 수 없습니다.
- **클래스 재정의(Redefinition) 시점**: 클래스의 완전한 교체가 필요할 때 사용합니다.
	- `Instrumentation.redefineClasses()` 메서드를 통해 트리거됩니다.
	- 클래스 변환기를 거치지 않고 직접 새 바이트코드를 제공합니다.
	- 마찬가지로 클래스 구조는 변경할 수 없습니다.

### 3.2 ClassFileTransformer 인터페이스

- 바이트코드 변환의 핵심은 `ClassFileTransformer` 인터페이스 구현체입니다.
- `transform` 메서드는 클래스 로드 시 호출되어 바이트코드를 변환합니다.

```java
public class MyClassTransformer implements ClassFileTransformer {
    @Override
    public byte[] transform(
            ClassLoader loader,
            String className,
            Class<?> classBeingRedefined,
            ProtectionDomain protectionDomain,
            byte[] classfileBuffer) {
        
        // 변환하려는 클래스인지 확인
        if (className.equals("com/example/TargetClass")) {
            // 바이트코드 조작 라이브러리(ASM, Javassist 등)를 사용하여 변환
            return transformBytes(classfileBuffer);
        }
        
        // 변환하지 않을 경우 원본 바이트코드 반환
        return null;
    }
}
```

### 3.3 주요 바이트코드 조작 라이브러리

- **ASM**: 가장 낮은 수준의 바이트코드 조작 라이브러리로, 높은 성능과 유연성을 제공합니다.
- **Javassist**: 더 높은 수준의 API를 제공하여 Java 코드와 유사한 문자열로 바이트코드를 조작할 수 있습니다.
- **ByteBuddy**: 현대적이고 타입 안전한 API를 제공하며, 복잡한 바이트코드 조작을 단순화합니다.

## 4. 실제 바이트코드 변환 예제

### 4.1 메서드 실행 시간 측정 에이전트

- 가장 일반적인 사용 사례인 메서드 실행 시간 측정 에이전트를 구현해 보겠습니다.
- 이 예제는 ByteBuddy를 사용하여 타겟 클래스의 모든 메서드에 시간 측정 로직을 삽입합니다.

#### Java Agent 클래스
```java
public class TimingAgent {
    public static void premain(String agentArgs, Instrumentation inst) {
        System.out.println("Timing Agent is starting...");
        
        new AgentBuilder.Default()
            .type(ElementMatchers.nameStartsWith("com.example"))
            .transform((builder, type, classLoader, module) -> 
                builder.method(ElementMatchers.any())
                       .intercept(MethodDelegation.to(TimingInterceptor.class))
            ).installOn(inst);
    }
}
```

#### 인터셉터 클래스
```java
public class TimingInterceptor {
    @RuntimeType
    public static Object intercept(@Origin Method method, 
                                  @SuperCall Callable<?> callable) throws Exception {
        long start = System.currentTimeMillis();
        
        try {
            return callable.call();
        } finally {
            long end = System.currentTimeMillis();
            System.out.println(method.getDeclaringClass().getSimpleName() + "." 
                              + method.getName() + ": " + (end - start) + "ms");
        }
    }
}
```

### 4.2 바이트코드 변환의 실제 흐름

특정 클래스의 바이트코드가 어떻게 변환되는지 살펴보겠습니다. 예를 들어, 다음과 같은 원본 코드가 있다고 가정합니다:

#### 원본 메서드
```java
public void processData(String data) {
    // 비즈니스 로직 처리
    System.out.println("Processing: " + data);
}
```

#### 변환 후 메서드(개념적 표현)
```java
public void processData(String data) {
    long startTime = System.currentTimeMillis();
    try {
        // 원본 비즈니스 로직 처리
        System.out.println("Processing: " + data);
    } finally {
        long endTime = System.currentTimeMillis();
        System.out.println("Method execution time: " + (endTime - startTime) + "ms");
    }
}
```

실제로는 이러한 변환이 바이트코드 수준에서 이루어집니다. 바이트코드 변환 전후를 개념적으로 보면:

#### 변환 전 바이트코드(간략화)
```
ALOAD 0
ALOAD 1
INVOKEVIRTUAL java/io/PrintStream.println (Ljava/lang/String;)V
RETURN
```

#### 변환 후 바이트코드(간략화)
```
INVOKESTATIC java/lang/System.currentTimeMillis ()J
LSTORE 2
ALOAD 0
ALOAD 1
INVOKEVIRTUAL java/io/PrintStream.println (Ljava/lang/String;)V
INVOKESTATIC java/lang/System.currentTimeMillis ()J
LSTORE 4
GETSTATIC java/lang/System.out Ljava/io/PrintStream;
NEW java/lang/StringBuilder
DUP
INVOKESPECIAL java/lang/StringBuilder.<init> ()V
LDC "Method execution time: "
INVOKEVIRTUAL java/lang/StringBuilder.append (Ljava/lang/String;)Ljava/lang/StringBuilder;
LLOAD 4
LLOAD 2
LSUB
INVOKEVIRTUAL java/lang/StringBuilder.append (J)Ljava/lang/StringBuilder;
LDC "ms"
INVOKEVIRTUAL java/lang/StringBuilder.append (Ljava/lang/String;)Ljava/lang/StringBuilder;
INVOKEVIRTUAL java/lang/StringBuilder.toString ()Ljava/lang/String;
INVOKEVIRTUAL java/io/PrintStream.println (Ljava/lang/String;)V
RETURN
```

## 5. Instrumentation API의 제약사항과 고려사항

### 5.1 기술적 제약사항

- **클래스 구조 변경 제한**: 필드 추가/삭제, 메서드 시그니처 변경, 슈퍼클래스 변경 등은 불가능합니다.
- **네이티브 메서드 변환 불가**: JNI(Java Native Interface)를 통해 구현된 네이티브 메서드는 변환할 수 없습니다.
- **성능 오버헤드**: 과도한 바이트코드 조작은 애플리케이션 성능에 영향을 줄 수 있습니다.
- **JVM 버전 의존성**: 일부 고급 기능은 특정 JVM 버전에서만 사용 가능합니다.

### 5.2 보안 고려사항

- **권한 관리**: Instrumentation API는 강력한 기능이므로 보안 관리자(Security Manager)를 통해 제한될 수 있습니다.
- **민감 정보 노출**: 로깅이나 모니터링 시 개인정보나 보안 데이터가 노출될 위험이 있습니다.
- **코드 무결성**: 악의적인 에이전트가 애플리케이션의 동작을 변경할 수 있습니다.

### 5.3 실무 적용 시 고려사항

- **선택적 계측**: 모든 클래스/메서드를 계측하면 오버헤드가 커지므로, 필요한 부분만 선택적으로 계측합니다.
- **예외 처리**: 바이트코드 변환 중 발생하는 예외를 적절히 처리하여 애플리케이션이 중단되지 않도록 합니다.
- **테스트**: 에이전트를 프로덕션에 적용하기 전에 충분한 테스트를 수행합니다.
- **로깅 제어**: 에이전트의 로깅 수준을 조절할 수 있는 메커니즘을 제공합니다.
- **성능 모니터링**: 에이전트 자체의 영향을 모니터링합니다.

## 6. 실제 활용 사례

### 6.1 애플리케이션 성능 모니터링(APM)

- **New Relic, AppDynamics, Pinpoint**: 이러한 APM 도구들은 Instrumentation API를 사용하여 실시간으로 애플리케이션 성능을 측정합니다.
- 메서드 실행 시간, 트랜잭션 추적, 외부 API 호출, DB 쿼리 등을 모니터링합니다.
- 성능 병목 현상을 식별하고 진단하는 데 도움을 줍니다.

### 6.2 코드 커버리지 및 테스트

- **JaCoCo, Cobertura**: 테스트 중에 코드 실행 경로를 추적하여 커버리지 지표를 생성합니다.
- 실행된 코드와 실행되지 않은 코드를 시각적으로 표시하여 테스트 품질을 향상시킵니다.

### 6.3 hot reloading 및 디버깅

- **JRebel, Spring Boot DevTools**: 코드 변경을 감지하고 애플리케이션을 재시작하지 않고 클래스를 다시 로드합니다.
- 개발 주기를 단축하고 생산성을 향상시킵니다.
- **Java Debug Wire Protocol (JDWP)**: 디버거와 JVM 간의 통신을 위한 프로토콜도 Instrumentation 개념을 기반으로 합니다.

### 6.4 보안 및 규정 준수

- **보안 정책 적용**: 특정 API 호출을 감시하거나 제한하여 보안 정책을 시행합니다.
- **감사 및 로깅**: 중요한 작업의 감사 추적을 위해 추가 로깅을 삽입합니다.
- **데이터 유출 방지**: 민감한 정보의 처리를 감시하고 제어합니다.

## 7. 결론 및 미래 전망

- Java Instrumentation API는 소스 코드 수정 없이 런타임에 애플리케이션 동작을 감시하고 변경할 수 있는 강력한 메커니즘을 제공합니다.
- 이 기술은 APM, 테스팅, 디버깅, 보안 등 다양한 영역에서 널리 활용되고 있습니다.
- 미래에는 Java Platform Module System(JPMS)과의 더 나은 통합, 더 정교한 바이트코드 조작 기능, 그리고 성능 개선이 기대됩니다.
- 점점 더 복잡해지는 분산 시스템 환경에서 관측성(Observability)과 모니터링의 중요성이 증가함에 따라, Instrumentation API의 중요성도 계속 커질 것으로 예상됩니다.